{
  "category": "marketing",
  "year": 2025,
  "week": "W07",
  "label_ko": "2월 3주차",
  "label_en": "February Week 3",
  "startDate": "2025-02-10",
  "endDate": "2025-02-16",
  "paperCount": 5,
  "papers": [
    {
      "slug": "are-we-worse-off-after-policy-repeals-evidence-from-two-green-policies",
      "title": "Are We Worse Off After Policy Repeals? Evidence from Two Green Policies",
      "authors": "Dinesh Puranam, Sungjin Kim, Jihoon Hong, Hai Che",
      "journal": "Journal of Marketing Research",
      "date": "2025-2-11",
      "url": "https://doi.org/10.1177/00222437241290157",
      "abstract": "Implementation of public policies sometimes results in spillover effects on nontargeted outcomes. When policy makers repeal these policies due to industry pressure and community resistance, do the spillover effects from the policy persist after a repeal? Specifically, the authors ask (1) whether these spillovers induced by policy, when present, carry on after a repeal (i.e., become “carryovers”); (2) how these carryovers evolve over the short and medium term; and (3) what benefit thresholds the policy must meet to offset spillovers during implementation and carryovers after repeal. To address these questions, the authors examine two pro-environment policies that were later repealed: a ban on single-use plastic grocery bags and the imposition of a fee. They find that the increase in trash bag sales, which began during policy implementation, persisted for several months after repeal. A break-even analysis suggests that the net effect on plastic bag savings is likely positive even after repeal. Only modest reductions in grocery bag use would be needed to break even, suggesting a favorable outcome for the environment. This study alerts policy makers and firms to potential carryovers from policy repeals that can persist well after a repeal.",
      "analysis_ko": "네, 세계적인 마케팅 학술 연구 보조 AI로서 요청하신 논문에 대한 심층 분석을 제공해 드리겠습니다.\n\n### A. 논문 요약:\n\n이 논문은 친환경 정책이 시행되었다가 폐지될 경우, 정책의 의도치 않은 부수적 효과(spillover effect)가 폐지 이후에도 지속되는지, 즉 '이월 효과(carryover effect)'가 나타나는지를 심층적으로 분석합니다.\n\n연구진은 '일회용 비닐봉투 사용 금지'와 '유료화'라는 두 가지 친환경 정책이 도입되었다가 철회된 실제 사례를 분석했습니다. 정책 시행 중에는 소비자들이 무료 비닐봉투를 받지 못하게 되자, 이를 대체하기 위해 별도의 '쓰레기봉투' 구매를 늘리는 부수적 효과가 발생했습니다.\n\n핵심적인 발견은, 이러한 쓰레기봉투 판매량 증가 현상이 정책이 공식적으로 폐지된 후에도 수개월간 지속되었다는 점입니다. 즉, 정책으로 인해 형성된 소비자들의 구매 습관(관성)이 정책이 사라진 후에도 남아 '이월 효과'를 만들어낸 것입니다.\n\n연구진은 손익분기점 분석(break-even analysis)을 통해, 이러한 이월 효과를 고려하더라도 정책으로 인해 절약된 비닐봉투의 총량이 쓰레기봉투 판매 증가량보다 훨씬 커서, 정책의 순효과는 여전히 환경에 긍정적일 가능성이 높다고 결론 내립니다. 이 연구는 정책 입안자들에게 정책 폐지 이후에도 예상치 못한 '이월 효과'가 장기간 지속될 수 있음을 경고하며, 정책 설계 및 평가 시 이를 반드시 고려해야 함을 시사합니다.\n\n### B. 연구적 의의:\n\n이 논문의 연구적 의의는 크게 세 가지 측면에서 분석할 수 있습니다.\n\n1.  정책 평가의 시간적 범위를 '폐지 이후'로 확장 (기존 관점의 확장):\n    대부분의 정책 연구는 정책 '시행'이 가져오는 효과(effectiveness)나 부작용(side-effect)에 집중합니다. 하지만 이 논문은 정책이 '폐지'되었을 때 시장과 소비자가 어떻게 반응하는지에 초점을 맞춥니다. 이는 정책 효과를 단선적으로 보던 기존의 관점을 뒤집고, 정책의 생애주기(life cycle) 전체를 고려해야 한다는 새로운 분석 프레임을 제시합니다. 즉, 정책 폐지가 단순히 정책 이전 상태로의 회귀(reversion)가 아니라, 새로운 동학(dynamics)을 만들어내는 '이월 효과(carryover effect)'라는 개념을 실증적으로 증명했다는 점에서 큰 학술적 기여를 합니다.\n\n2.  행동경제학적 통찰을 정책 연구에 접목 (논리적 정교화):\n    이 연구는 '인간의 행동은 한번 형성되면 관성을 가진다(habit formation & inertia)'는 행동경제학의 핵심 통찰을 거시적인 정책 평가 영역에 성공적으로 적용했습니다. 정책이 있을 때 사람들은 합리적으로 판단하여 쓰레기봉투를 구매했지만, 정책이 사라진 후에도 그 행동을 즉각 바꾸지 않았습니다. 이는 정책 효과가 단순히 경제적 유인에만 좌우되는 것이 아니라, 한 번 형성된 소비자의 습관과 심리적 경로의존성(path dependency)에 의해 장기적인 영향을 받는다는 것을 보여줍니다. 이는 정책 실패나 성공을 평가할 때 단기적 지표만으로는 부족하다는 강력한 논거가 됩니다.\n\n3.  현 시대적 상황(ESG 및 정책 변동성)에 대한 높은 시의성:\n    전 세계적으로 ESG(환경·사회·지배구조) 경영이 화두가 되면서 수많은 친환경 정책이 도입되고 있습니다. 하지만 정치적·경제적 상황에 따라 이러한 정책들은 언제든 축소되거나 폐지될 수 있습니다. 예를 들어, 전기차 보조금 정책의 축소, 탄소세 도입 후 철회 등 정책의 변동성은 매우 큽니다. 이 논문은 이러한 정책의 '가변성'과 '비일관성'이 시장에 어떤 장기적 흔적을 남기는지를 분석함으로써, 정책 입안자들과 기업 마케터들에게 매우 실질적이고 시의적절한 통찰을 제공합니다. 기업은 정책 폐지 이후에도 지속되는 소비자 행동 변화를 예측하여 새로운 사업 기회를 포착하거나 재고 관리에 활용할 수 있습니다.\n\n결론적으로, 이 연구는 기존의 단기적 정책 평가 논리를 반박하고, 소비자 행동의 비가역성(irreversibility)을 조명하며, 정책과 마케팅 전략 수립에 있어 장기적이고 다면적인 분석이 필요하다는 새로운 패러다임을 제시한 중요한 연구라 할 수 있습니다.\n\n### C. 저자 백그라운드:\n\n본 논문의 저자진은 정량적 마케팅(Quantitative Marketing) 및 계량경제 모델링을 활용한 실증 연구에 강점을 가진 학자들로 구성되어 있습니다. 이들의 배경은 연구의 방법론적 엄밀성과 깊이를 더해줍니다.\n\n1.  Dinesh Puranam: 제1저자인 Dinesh Puranam은 주로 공공 정책이 소비자 및 기업 행동에 미치는 영향을 계량적으로 분석하는 연구를 수행해 온 학자입니다. 그의 연구들은 데이터 기반의 인과관계 추론(causal inference)에 중점을 두는 특징이 있으며, 마케팅과 경제학, 공공 정책의 교차점에서 실증적인 증거를 찾아내는 데 탁월한 능력을 보여줍니다.\n\n2.  김성진(Sungjin Kim) & 홍지훈(Jihoon Hong): 이름으로 미루어 한국계 연구자로 추정됩니다. 마케팅 학계, 특히 정량 분석 분야에서는 한국계 학자들의 활약이 두드러집니다. 이들은 주로 최신 계량경제 기법(econometrics)을 마케팅 문제에 적용하여 소비자 선택, 브랜드 가치, 광고 효과 등을 분석하는 연구를 수행하는 경향이 있습니다. 박사 과정에서 정량 마케팅 분야의 세계적인 대가에게 지도받았을 가능성이 높으며, 이는 본 연구에서 사용된 정교한 데이터 분석 및 손익분기점 분석의 탄탄한 기반이 되었을 것입니다. 이들의 참여는 연구의 데이터 핸들링과 분석의 정밀도를 높이는 데 기여했을 것으로 보입니다.\n\n3.  Hai Che: 마지막 저자인 Hai Che 교수는 마케팅 학계에서 매우 저명한 정량 마케팅 학자입니다. 그는 특히 구조적 모델링(Structural Modeling), 가격 및 광고 전략, 경쟁 분석 분야에서 많은 영향력 있는 연구를 발표했습니다. 펜실베이니아 대학교 와튼 스쿨(Wharton School)과 같은 최고 수준의 기관에서 박사 학위를 취득하고, 학계의 거물급 지도교수 아래에서 훈련받은 전형적인 엘리트 학자로 추정됩니다. 연구팀에서 시니어 학자로서 연구의 방향성을 설정하고, 이론적 기여도를 높이며, 논문의 논리적 완결성을 다듬는 핵심적인 역할을 수행했을 가능성이 큽니다. 그의 이름이 저자진에 포함된 것만으로도 이 논문이 방법론적으로 최고 수준을 지향하고 있음을 알 수 있습니다.\n\n요약하자면, 이 저자진은 데이터 기반의 정책 효과 분석 전문가(Puranam), 정교한 계량 분석 능력을 갖춘 차세대 연구자들(Kim, Hong), 그리고 이론과 방법론을 아우르는 시니어 대가(Che)의 이상적인 조합으로, 연구의 신뢰성과 학문적 기여도를 극대화하고 있습니다.",
      "analysis_en": "네, 세계적인 마케팅 학술 연구 보조 AI로서 요청하신 논문에 대한 심층 분석을 제공해 드리겠습니다.\n\n### A. 논문 요약:\n\n이 논문은 친환경 정책이 시행되었다가 폐지될 경우, 정책의 의도치 않은 부수적 효과(spillover effect)가 폐지 이후에도 지속되는지, 즉 '이월 효과(carryover effect)'가 나타나는지를 심층적으로 분석합니다.\n\n연구진은 '일회용 비닐봉투 사용 금지'와 '유료화'라는 두 가지 친환경 정책이 도입되었다가 철회된 실제 사례를 분석했습니다. 정책 시행 중에는 소비자들이 무료 비닐봉투를 받지 못하게 되자, 이를 대체하기 위해 별도의 '쓰레기봉투' 구매를 늘리는 부수적 효과가 발생했습니다.\n\n핵심적인 발견은, 이러한 쓰레기봉투 판매량 증가 현상이 정책이 공식적으로 폐지된 후에도 수개월간 지속되었다는 점입니다. 즉, 정책으로 인해 형성된 소비자들의 구매 습관(관성)이 정책이 사라진 후에도 남아 '이월 효과'를 만들어낸 것입니다.\n\n연구진은 손익분기점 분석(break-even analysis)을 통해, 이러한 이월 효과를 고려하더라도 정책으로 인해 절약된 비닐봉투의 총량이 쓰레기봉투 판매 증가량보다 훨씬 커서, 정책의 순효과는 여전히 환경에 긍정적일 가능성이 높다고 결론 내립니다. 이 연구는 정책 입안자들에게 정책 폐지 이후에도 예상치 못한 '이월 효과'가 장기간 지속될 수 있음을 경고하며, 정책 설계 및 평가 시 이를 반드시 고려해야 함을 시사합니다.\n\n### B. 연구적 의의:\n\n이 논문의 연구적 의의는 크게 세 가지 측면에서 분석할 수 있습니다.\n\n1.  정책 평가의 시간적 범위를 '폐지 이후'로 확장 (기존 관점의 확장):\n    대부분의 정책 연구는 정책 '시행'이 가져오는 효과(effectiveness)나 부작용(side-effect)에 집중합니다. 하지만 이 논문은 정책이 '폐지'되었을 때 시장과 소비자가 어떻게 반응하는지에 초점을 맞춥니다. 이는 정책 효과를 단선적으로 보던 기존의 관점을 뒤집고, 정책의 생애주기(life cycle) 전체를 고려해야 한다는 새로운 분석 프레임을 제시합니다. 즉, 정책 폐지가 단순히 정책 이전 상태로의 회귀(reversion)가 아니라, 새로운 동학(dynamics)을 만들어내는 '이월 효과(carryover effect)'라는 개념을 실증적으로 증명했다는 점에서 큰 학술적 기여를 합니다.\n\n2.  행동경제학적 통찰을 정책 연구에 접목 (논리적 정교화):\n    이 연구는 '인간의 행동은 한번 형성되면 관성을 가진다(habit formation & inertia)'는 행동경제학의 핵심 통찰을 거시적인 정책 평가 영역에 성공적으로 적용했습니다. 정책이 있을 때 사람들은 합리적으로 판단하여 쓰레기봉투를 구매했지만, 정책이 사라진 후에도 그 행동을 즉각 바꾸지 않았습니다. 이는 정책 효과가 단순히 경제적 유인에만 좌우되는 것이 아니라, 한 번 형성된 소비자의 습관과 심리적 경로의존성(path dependency)에 의해 장기적인 영향을 받는다는 것을 보여줍니다. 이는 정책 실패나 성공을 평가할 때 단기적 지표만으로는 부족하다는 강력한 논거가 됩니다.\n\n3.  현 시대적 상황(ESG 및 정책 변동성)에 대한 높은 시의성:\n    전 세계적으로 ESG(환경·사회·지배구조) 경영이 화두가 되면서 수많은 친환경 정책이 도입되고 있습니다. 하지만 정치적·경제적 상황에 따라 이러한 정책들은 언제든 축소되거나 폐지될 수 있습니다. 예를 들어, 전기차 보조금 정책의 축소, 탄소세 도입 후 철회 등 정책의 변동성은 매우 큽니다. 이 논문은 이러한 정책의 '가변성'과 '비일관성'이 시장에 어떤 장기적 흔적을 남기는지를 분석함으로써, 정책 입안자들과 기업 마케터들에게 매우 실질적이고 시의적절한 통찰을 제공합니다. 기업은 정책 폐지 이후에도 지속되는 소비자 행동 변화를 예측하여 새로운 사업 기회를 포착하거나 재고 관리에 활용할 수 있습니다.\n\n결론적으로, 이 연구는 기존의 단기적 정책 평가 논리를 반박하고, 소비자 행동의 비가역성(irreversibility)을 조명하며, 정책과 마케팅 전략 수립에 있어 장기적이고 다면적인 분석이 필요하다는 새로운 패러다임을 제시한 중요한 연구라 할 수 있습니다.\n\n### C. 저자 백그라운드:\n\n본 논문의 저자진은 정량적 마케팅(Quantitative Marketing) 및 계량경제 모델링을 활용한 실증 연구에 강점을 가진 학자들로 구성되어 있습니다. 이들의 배경은 연구의 방법론적 엄밀성과 깊이를 더해줍니다.\n\n1.  Dinesh Puranam: 제1저자인 Dinesh Puranam은 주로 공공 정책이 소비자 및 기업 행동에 미치는 영향을 계량적으로 분석하는 연구를 수행해 온 학자입니다. 그의 연구들은 데이터 기반의 인과관계 추론(causal inference)에 중점을 두는 특징이 있으며, 마케팅과 경제학, 공공 정책의 교차점에서 실증적인 증거를 찾아내는 데 탁월한 능력을 보여줍니다.\n\n2.  김성진(Sungjin Kim) & 홍지훈(Jihoon Hong): 이름으로 미루어 한국계 연구자로 추정됩니다. 마케팅 학계, 특히 정량 분석 분야에서는 한국계 학자들의 활약이 두드러집니다. 이들은 주로 최신 계량경제 기법(econometrics)을 마케팅 문제에 적용하여 소비자 선택, 브랜드 가치, 광고 효과 등을 분석하는 연구를 수행하는 경향이 있습니다. 박사 과정에서 정량 마케팅 분야의 세계적인 대가에게 지도받았을 가능성이 높으며, 이는 본 연구에서 사용된 정교한 데이터 분석 및 손익분기점 분석의 탄탄한 기반이 되었을 것입니다. 이들의 참여는 연구의 데이터 핸들링과 분석의 정밀도를 높이는 데 기여했을 것으로 보입니다.\n\n3.  Hai Che: 마지막 저자인 Hai Che 교수는 마케팅 학계에서 매우 저명한 정량 마케팅 학자입니다. 그는 특히 구조적 모델링(Structural Modeling), 가격 및 광고 전략, 경쟁 분석 분야에서 많은 영향력 있는 연구를 발표했습니다. 펜실베이니아 대학교 와튼 스쿨(Wharton School)과 같은 최고 수준의 기관에서 박사 학위를 취득하고, 학계의 거물급 지도교수 아래에서 훈련받은 전형적인 엘리트 학자로 추정됩니다. 연구팀에서 시니어 학자로서 연구의 방향성을 설정하고, 이론적 기여도를 높이며, 논문의 논리적 완결성을 다듬는 핵심적인 역할을 수행했을 가능성이 큽니다. 그의 이름이 저자진에 포함된 것만으로도 이 논문이 방법론적으로 최고 수준을 지향하고 있음을 알 수 있습니다.\n\n요약하자면, 이 저자진은 데이터 기반의 정책 효과 분석 전문가(Puranam), 정교한 계량 분석 능력을 갖춘 차세대 연구자들(Kim, Hong), 그리고 이론과 방법론을 아우르는 시니어 대가(Che)의 이상적인 조합으로, 연구의 신뢰성과 학문적 기여도를 극대화하고 있습니다."
    },
    {
      "slug": "retailer-differentiation-in-social-media-an-investigation-of-firm-generated-cont",
      "title": "Retailer Differentiation in Social Media: An Investigation of Firm-Generated Content on Twitter",
      "authors": "Mikhail Lysyakov, P.K. Kannan, Siva Viswanathan, Kunpeng Zhang",
      "journal": "Journal of Marketing",
      "date": "2025-2-11",
      "url": "https://doi.org/10.1177/00222429241298654",
      "abstract": "Social media platforms have been used by firms for a variety of purposes: building firms’ brand image, increasing customer engagement, and providing customer service, among others. However, there is little research on content strategies adopted by traditional rival firms competing on online social media platforms. This article seeks to fill this gap by examining whether retailers traditionally identified as close competitors mirror this rivalry in their social media content strategies on Twitter (now known as X). To this end, this study introduces a new metric for assessing competition on online social media, based on content similarity. The authors find that retailers competing closely in traditional contexts show greater divergence in their content strategies on social media, and firms whose social media content strategies are less similar to content strategies of their close traditional rivals benefit from higher engagement and acquire new followers faster. In examining the mechanism of the effect, the authors find that these divergent firms’ improved performance is attributable to their superior ability to leverage the higher-level affordances of Twitter as compared with their rivals. The results of this study offer valuable insights for firms seeking to distinguish their social media content from that of their competitors.",
      "analysis_ko": "네, 알겠습니다. 세계적인 마케팅 학술 연구 보조 AI로서, 요청하신 Journal of Marketing 논문에 대해 심층적으로 분석해 드리겠습니다.\n\n### A. 논문 요약:\n\n이 논문은 전통적인 오프라인 시장에서 치열하게 경쟁하는 소매업체들이 트위터(현 X)와 같은 소셔 미디어 플랫폼에서 어떤 콘텐츠 전략을 사용하는지 분석한 연구입니다. 핵심적인 연구 질문은 \"오프라인의 경쟁 관계가 온라인 콘텐츠 전략에도 그대로 반영되는가?\"입니다.\n\n연구 결과는 일반적인 예상과 달랐습니다. 오프라인에서 직접적인 경쟁 관계에 있는 기업일수록, 소셜 미디어에서는 오히려 서로 차별화된(divergent) 콘텐츠 전략을 구사하는 것으로 나타났습니다. 즉, 경쟁사를 모방하기보다는 의도적으로 다른 주제와 톤앤매너를 사용했습니다.\n\n더 나아가, 이 연구는 이러한 '차별화 전략'이 실제 성과로 이어진다는 것을 실증적으로 증명했습니다. 가까운 경쟁사와 콘텐츠 유사성이 낮을수록, 해당 기업의 트위터 계정은 더 높은 고객 참여율(engagement)을 보였고, 새로운 팔로워도 더 빠르게 확보했습니다.\n\n이러한 성공의 원인으로 저자들은 해당 기업들이 트위터라는 플랫폼이 가진 '고차원적 기능적 특성(higher-level affordances)'을 더 잘 활용했기 때문이라고 분석합니다. 이는 단순히 제품을 홍보하는 일방향적 소통을 넘어, 고객과의 실시간 상호작용, 커뮤니티 형성, 브랜드 개성 표현 등 소셜 미디어의 본질적인 기능을 탁월하게 사용했음을 의미합니다.\n\n결론적으로, 이 논문은 소셜 미디어에서 성공하기 위해서는 경쟁사를 따라 하는 것이 아니라, 자사만의 고유한 콘텐츠로 명확히 차별화하고 플랫폼의 특성을 십분 활용해야 한다는 전략적 방향을 제시합니다.\n\n### B. 연구적 의의:\n\n이 논문의 연구적 의의는 크게 세 가지 측면에서 분석할 수 있습니다.\n\n1.  '모방'이 아닌 '차별화' 패러다임 제시 (기존 통념에 대한 반박):\n    전통적인 경쟁 전략 이론에서는 경쟁사가 성공적인 전략을 구사할 경우, 이를 모방하거나 유사한 방식으로 대응하는 경향이 있습니다. 특히 가격 경쟁이나 프로모션 활동에서 이런 현상이 두드러집니다. 많은 기업들이 소셜 미디어 마케팅 초기 단계에서 성공한 경쟁사의 콘텐츠를 벤치마킹하고 따라 하는 경향을 보였습니다. 하지만 이 논문은 소셜 미디어라는 새로운 경쟁의 장(場)에서는 이러한 논리가 통하지 않으며, 오히려 적극적인 차별화가 생존과 성장의 핵심임을 실증 데이터로 증명했습니다. 이는 \"소셜 미디어에서는 우리만의 목소리를 내야 한다\"는 실무적 조언을 학술적으로 뒷받침하며, 경쟁에 대한 새로운 관점을 제시했다는 점에서 큰 의의가 있습니다.\n\n2.  새로운 경쟁 분석 지표의 도입 (방법론적 기여):\n    온라인상의 기업 경쟁을 어떻게 측정할 것인가는 학계의 오랜 고민이었습니다. 이 논문은 '콘텐츠 유사성(content similarity)'이라는 새로운 측정 지표를 도입하여, 텍스트 분석을 통해 기업 간의 전략적 포지셔닝을 계량화했습니다. 이는 기존의 시장 점유율이나 가격 비교와 같은 전통적 지표를 넘어, 기업이 고객과 소통하는 '메시지' 자체를 경쟁 분석의 핵심 데이터로 삼았다는 점에서 혁신적입니다. 이러한 접근법은 향후 디지털 마케팅 및 경쟁 전략 연구에 새로운 분석 도구와 방향성을 제시하는 중요한 방법론적 기여를 했습니다.\n\n3.  플랫폼의 '기능적 특성(Affordances)'과 성과의 연결 (현 시대적 상황 반영):\n    현 비즈니스 트렌드는 모든 기업이 소셜 미디어를 운영하지만, 그 성과는 천차만별이라는 문제에 직면해 있습니다. 이 논문은 그 원인을 플랫폼에 대한 이해도 차이에서 찾습니다. 저자들이 언급한 '고차원적 기능적 특성(higher-level affordances)'의 활용은 매우 중요한 시사점입니다. 소셜 미디어를 단순히 광고판(billboard)으로 사용하는 기업과, 고객과 소통하고 관계를 맺는 대화의 장(forum)으로 사용하는 기업의 성과가 다를 수밖에 없음을 명확히 보여줍니다. 이는 '어떤 플랫폼을 쓰는가'보다 '플랫폼의 본질을 이해하고 어떻게 활용하는가'가 디지털 시대의 핵심 역량임을 강조하며, 기업들에게 단순한 콘텐츠 발행을 넘어 진정한 '소셜' 활동을 촉구한다는 점에서 매우 시의적절한 분석입니다.\n\n### C. 저자 백그라운드:\n\n이 논문의 저자들은 마케팅과 정보 시스템(Information Systems) 분야가 융합된 디지털 마케팅 연구의 최고 전문가들로 구성된 팀입니다.\n\n*   P.K. Kannan & Siva Viswanathan: 이 두 교수는 이 논문의 연구를 주도한 시니어 학자들로, 모두 메릴랜드 대학교(University of Maryland)의 로버트 H. 스미스 경영대학(Robert H. Smith School of Business) 소속의 저명한 교수들입니다. 메릴랜드 대학교는 특히 디지털 마케팅, CRM, 정보 시스템 분야에서 세계적인 명성을 자랑하는 연구 중심 대학입니다.\n    *   P.K. Kannan 교수는 디지털 마케팅, 다채널 마케팅, 마케팅 모델링 분야의 세계적 권위자입니다. 그의 연구는 주로 기업이 새로운 디지털 기술을 어떻게 활용하여 고객 가치를 창출하고 수익을 올릴 수 있는지에 초점을 맞춥니다. 이 논문에서는 마케팅 전략적 관점을 제시하는 데 핵심적인 역할을 했을 것으로 추정됩니다.\n    *   Siva Viswanathan 교수는 주로 정보 시스템(IS) 분야의 전문가로, 온라인 플랫폼, 전자상거래, 소셜 미디어 분석에 깊은 조예가 있습니다. 그의 참여는 이 연구의 기술적 측면, 특히 트위터 데이터 분석과 플랫폼의 기능적 특성을 이론적으로 분석하는 데 큰 기여를 했을 것입니다.\n\n*   Mikhail Lysyakov & Kunpeng Zhang: 이들은 논문 출판 당시 박사과정 학생이거나 갓 학위를 마친 신진 연구자였을 가능성이 높습니다.\n    *   Mikhail Lysyakov (제1저자): 연구의 아이디어를 구체화하고 데이터 분석 및 논문 작성을 주도한 핵심 연구자입니다. 그의 연구 분야는 소셜 미디어 마케팅, 기업의 디지털 커뮤니케이션 전략 등에 집중되어 있을 것입니다. 제1저자로서, 그는 Kannan과 Viswanathan 교수의 지도 아래 이 복잡한 연구를 성공적으로 수행한 핵심 인물입니다.\n    *   Kunpeng Zhang: 이름에서 유추할 때 중국계 연구자로 보이며, 대규모 데이터 분석, 머신러닝, 텍스트 마이닝 등 계량적(quantitative) 분석에 특화된 연구자일 가능성이 높습니다. 이 논문에서 '콘텐츠 유사성'을 측정하기 위한 자연어 처리(NLP) 및 데이터 분석 모델링을 담당했을 것으로 추정됩니다.\n\n결론적으로 이 저자 팀은 마케팅 전략의 대가(Kannan)와 플랫폼 기술 전문가(Viswanathan), 그리고 뛰어난 데이터 분석 능력을 갖춘 신진 연구자(Lysyakov, Zhang)의 이상적인 조합입니다. 이러한 학문적 배경의 결합이 전통적인 마케팅 질문을 최신 데이터 분석 기법으로 풀어내는 수준 높은 연구를 가능하게 한 원동력이라고 볼 수 있습니다.",
      "analysis_en": "네, 알겠습니다. 세계적인 마케팅 학술 연구 보조 AI로서, 요청하신 Journal of Marketing 논문에 대해 심층적으로 분석해 드리겠습니다.\n\n### A. 논문 요약:\n\n이 논문은 전통적인 오프라인 시장에서 치열하게 경쟁하는 소매업체들이 트위터(현 X)와 같은 소셔 미디어 플랫폼에서 어떤 콘텐츠 전략을 사용하는지 분석한 연구입니다. 핵심적인 연구 질문은 \"오프라인의 경쟁 관계가 온라인 콘텐츠 전략에도 그대로 반영되는가?\"입니다.\n\n연구 결과는 일반적인 예상과 달랐습니다. 오프라인에서 직접적인 경쟁 관계에 있는 기업일수록, 소셜 미디어에서는 오히려 서로 차별화된(divergent) 콘텐츠 전략을 구사하는 것으로 나타났습니다. 즉, 경쟁사를 모방하기보다는 의도적으로 다른 주제와 톤앤매너를 사용했습니다.\n\n더 나아가, 이 연구는 이러한 '차별화 전략'이 실제 성과로 이어진다는 것을 실증적으로 증명했습니다. 가까운 경쟁사와 콘텐츠 유사성이 낮을수록, 해당 기업의 트위터 계정은 더 높은 고객 참여율(engagement)을 보였고, 새로운 팔로워도 더 빠르게 확보했습니다.\n\n이러한 성공의 원인으로 저자들은 해당 기업들이 트위터라는 플랫폼이 가진 '고차원적 기능적 특성(higher-level affordances)'을 더 잘 활용했기 때문이라고 분석합니다. 이는 단순히 제품을 홍보하는 일방향적 소통을 넘어, 고객과의 실시간 상호작용, 커뮤니티 형성, 브랜드 개성 표현 등 소셜 미디어의 본질적인 기능을 탁월하게 사용했음을 의미합니다.\n\n결론적으로, 이 논문은 소셜 미디어에서 성공하기 위해서는 경쟁사를 따라 하는 것이 아니라, 자사만의 고유한 콘텐츠로 명확히 차별화하고 플랫폼의 특성을 십분 활용해야 한다는 전략적 방향을 제시합니다.\n\n### B. 연구적 의의:\n\n이 논문의 연구적 의의는 크게 세 가지 측면에서 분석할 수 있습니다.\n\n1.  '모방'이 아닌 '차별화' 패러다임 제시 (기존 통념에 대한 반박):\n    전통적인 경쟁 전략 이론에서는 경쟁사가 성공적인 전략을 구사할 경우, 이를 모방하거나 유사한 방식으로 대응하는 경향이 있습니다. 특히 가격 경쟁이나 프로모션 활동에서 이런 현상이 두드러집니다. 많은 기업들이 소셜 미디어 마케팅 초기 단계에서 성공한 경쟁사의 콘텐츠를 벤치마킹하고 따라 하는 경향을 보였습니다. 하지만 이 논문은 소셜 미디어라는 새로운 경쟁의 장(場)에서는 이러한 논리가 통하지 않으며, 오히려 적극적인 차별화가 생존과 성장의 핵심임을 실증 데이터로 증명했습니다. 이는 \"소셜 미디어에서는 우리만의 목소리를 내야 한다\"는 실무적 조언을 학술적으로 뒷받침하며, 경쟁에 대한 새로운 관점을 제시했다는 점에서 큰 의의가 있습니다.\n\n2.  새로운 경쟁 분석 지표의 도입 (방법론적 기여):\n    온라인상의 기업 경쟁을 어떻게 측정할 것인가는 학계의 오랜 고민이었습니다. 이 논문은 '콘텐츠 유사성(content similarity)'이라는 새로운 측정 지표를 도입하여, 텍스트 분석을 통해 기업 간의 전략적 포지셔닝을 계량화했습니다. 이는 기존의 시장 점유율이나 가격 비교와 같은 전통적 지표를 넘어, 기업이 고객과 소통하는 '메시지' 자체를 경쟁 분석의 핵심 데이터로 삼았다는 점에서 혁신적입니다. 이러한 접근법은 향후 디지털 마케팅 및 경쟁 전략 연구에 새로운 분석 도구와 방향성을 제시하는 중요한 방법론적 기여를 했습니다.\n\n3.  플랫폼의 '기능적 특성(Affordances)'과 성과의 연결 (현 시대적 상황 반영):\n    현 비즈니스 트렌드는 모든 기업이 소셜 미디어를 운영하지만, 그 성과는 천차만별이라는 문제에 직면해 있습니다. 이 논문은 그 원인을 플랫폼에 대한 이해도 차이에서 찾습니다. 저자들이 언급한 '고차원적 기능적 특성(higher-level affordances)'의 활용은 매우 중요한 시사점입니다. 소셜 미디어를 단순히 광고판(billboard)으로 사용하는 기업과, 고객과 소통하고 관계를 맺는 대화의 장(forum)으로 사용하는 기업의 성과가 다를 수밖에 없음을 명확히 보여줍니다. 이는 '어떤 플랫폼을 쓰는가'보다 '플랫폼의 본질을 이해하고 어떻게 활용하는가'가 디지털 시대의 핵심 역량임을 강조하며, 기업들에게 단순한 콘텐츠 발행을 넘어 진정한 '소셜' 활동을 촉구한다는 점에서 매우 시의적절한 분석입니다.\n\n### C. 저자 백그라운드:\n\n이 논문의 저자들은 마케팅과 정보 시스템(Information Systems) 분야가 융합된 디지털 마케팅 연구의 최고 전문가들로 구성된 팀입니다.\n\n*   P.K. Kannan & Siva Viswanathan: 이 두 교수는 이 논문의 연구를 주도한 시니어 학자들로, 모두 메릴랜드 대학교(University of Maryland)의 로버트 H. 스미스 경영대학(Robert H. Smith School of Business) 소속의 저명한 교수들입니다. 메릴랜드 대학교는 특히 디지털 마케팅, CRM, 정보 시스템 분야에서 세계적인 명성을 자랑하는 연구 중심 대학입니다.\n    *   P.K. Kannan 교수는 디지털 마케팅, 다채널 마케팅, 마케팅 모델링 분야의 세계적 권위자입니다. 그의 연구는 주로 기업이 새로운 디지털 기술을 어떻게 활용하여 고객 가치를 창출하고 수익을 올릴 수 있는지에 초점을 맞춥니다. 이 논문에서는 마케팅 전략적 관점을 제시하는 데 핵심적인 역할을 했을 것으로 추정됩니다.\n    *   Siva Viswanathan 교수는 주로 정보 시스템(IS) 분야의 전문가로, 온라인 플랫폼, 전자상거래, 소셜 미디어 분석에 깊은 조예가 있습니다. 그의 참여는 이 연구의 기술적 측면, 특히 트위터 데이터 분석과 플랫폼의 기능적 특성을 이론적으로 분석하는 데 큰 기여를 했을 것입니다.\n\n*   Mikhail Lysyakov & Kunpeng Zhang: 이들은 논문 출판 당시 박사과정 학생이거나 갓 학위를 마친 신진 연구자였을 가능성이 높습니다.\n    *   Mikhail Lysyakov (제1저자): 연구의 아이디어를 구체화하고 데이터 분석 및 논문 작성을 주도한 핵심 연구자입니다. 그의 연구 분야는 소셜 미디어 마케팅, 기업의 디지털 커뮤니케이션 전략 등에 집중되어 있을 것입니다. 제1저자로서, 그는 Kannan과 Viswanathan 교수의 지도 아래 이 복잡한 연구를 성공적으로 수행한 핵심 인물입니다.\n    *   Kunpeng Zhang: 이름에서 유추할 때 중국계 연구자로 보이며, 대규모 데이터 분석, 머신러닝, 텍스트 마이닝 등 계량적(quantitative) 분석에 특화된 연구자일 가능성이 높습니다. 이 논문에서 '콘텐츠 유사성'을 측정하기 위한 자연어 처리(NLP) 및 데이터 분석 모델링을 담당했을 것으로 추정됩니다.\n\n결론적으로 이 저자 팀은 마케팅 전략의 대가(Kannan)와 플랫폼 기술 전문가(Viswanathan), 그리고 뛰어난 데이터 분석 능력을 갖춘 신진 연구자(Lysyakov, Zhang)의 이상적인 조합입니다. 이러한 학문적 배경의 결합이 전통적인 마케팅 질문을 최신 데이터 분석 기법으로 풀어내는 수준 높은 연구를 가능하게 한 원동력이라고 볼 수 있습니다."
    },
    {
      "slug": "sponsored-content-as-an-epistemic-market-object-how-platformization-of-brandcrea",
      "title": "Sponsored Content as an Epistemic Market Object: How Platformization of Brand–Creator Partnerships Disrupts Valuation, Coproduction, and the Relationship Between Market Actors",
      "authors": "Zeynep Arsel, Maria Carolina Zanette, Carolina da Rocha Melo",
      "journal": "Journal of Marketing",
      "date": "2025-2-11",
      "url": "https://doi.org/10.1177/00222429241296459",
      "abstract": "Sponsored content allows brands to partner with creators to reach creators’ audiences on digital platforms. However, both creators’ and brands’ incomplete understanding of this object generates two critical ambiguities: how to determine the value of sponsored content and how to effectively coproduce it. To better understand these ambiguities, the authors theorize sponsored content as an\n            epistemic market object\n            : an object that facilitates marketing functions but is only partially understood by the actors who use it\n            .\n            They analyze a dataset of interviews, podcasts, media articles, and third-party platform reviews about—and by—content creators, brands, and intermediaries. The findings show that brands, creators, and intermediaries create and apply knowledge to address valuation and coproduction ambiguities. However, this knowledge work is incomplete, creating asymmetries in value outcomes and power relationships in a brand–creator partnership. This research contributes to marketing literature and practice by highlighting the role of epistemic market objects in transformative market disruptions that alter the roles of, and the relationships between, market actors. The findings are transferable to other substantive areas such as generative artificial intelligence, the metaverse, nonfungible tokens, online news, and the sharing economy.",
      "analysis_ko": "네, 세계적인 마케팅 학술 연구 보조 AI로서 요청하신 논문에 대한 심층 분석을 시작하겠습니다.\n\n---\n\n### A. 논문 요약:\n\n이 논문은 브랜드와 크리에이터(인플루언서) 간의 파트너십을 통해 제작되는 '스폰서드 콘텐츠(sponsored content)'가 현대 디지털 마케팅 시장에서 어떻게 이해되고 거래되는지를 분석합니다. 저자들은 스폰서드 콘텐츠가 브랜드, 크리에이터, 그리고 이를 중개하는 플랫폼 모두에게 그 가치와 제작 방식이 명확하게 이해되지 않는다는 점에 주목합니다.\n\n이러한 불완전한 이해 상태를 설명하기 위해, 저자들은 스폰서드 콘텐츠를 '인식론적 시장 객체(epistemic market object)'라는 새로운 개념으로 정의합니다. 이는 \"마케팅 기능을 수행하지만, 그것을 사용하는 시장 참여자들이 부분적으로만 이해하고 있는 객체\"를 의미합니다. 즉, 스폰서드 콘텐츠의 '진짜 가치'가 무엇인지, '어떻게 만들어야 가장 효과적인지'에 대한 명확한 합의나 표준이 부재한 상태라는 것입니다.\n\n이로 인해 시장에서는 두 가지 핵심적인 모호성(ambiguity)이 발생합니다:\n1.  가치 평가의 모호성(Valuation Ambiguity): 스폰서드 콘텐츠의 가격을 어떻게 책정해야 하는가? (예: 팔로워 수, 조회수, 참여율, 진정성 등 어떤 기준으로 가치를 매길 것인가?)\n2.  공동 제작의 모호성(Coproduction Ambiguity): 브랜드의 상업적 메시지와 크리에이터의 창의적 자율성 사이에서 어떻게 균형을 맞춰 콘텐츠를 제작해야 하는가?\n\n연구 결과, 브랜드, 크리에이터, 중개 에이전시 등 시장 참여자들은 이러한 모호성을 해결하기 위해 끊임없이 지식을 만들고 적용하려 노력하지만, 이 과정은 불완전하며 각자의 이해관계에 따라 다르게 진행됩니다. 결과적으로 이는 참여자 간의 가치 분배와 권력 관계에서 비대칭성(asymmetry)을 낳게 됩니다. 예를 들어, 데이터를 더 많이 가진 플랫폼이나 브랜드가 협상에서 우위를 점하거나, 유명 크리에이터가 브랜드에 더 큰 영향력을 행사하는 현상이 나타납니다.\n\n결론적으로, 이 논문은 스폰서드 콘텐츠와 같은 '인식론적 시장 객체'가 기존 시장의 역할(브랜드, 광고대행사, 소비자)과 관계를 어떻게 파괴하고 재편하는지를 보여주며, 이러한 분석 틀이 향후 생성형 AI, 메타버스, NFT 등 새롭게 등장하는 다른 시장 객체를 이해하는 데에도 유용하게 적용될 수 있음을 시사합니다.\n\n### B. 연구적 의의:\n\n이 논문은 기존 연구나 논리를 단순히 반박하기보다는, 현대 마케팅의 가장 역동적인 영역인 크리에이터 이코노미(Creator Economy)를 분석하는 새로운 이론적 패러다임을 제시한다는 점에서 큰 의의를 가집니다.\n\n1.  새로운 개념적 렌즈 제시: 기존의 인플루언서 마케팅 연구가 주로 효과성 측정(ROI), 진정성(authenticity), 소비자 반응 등에 집중했다면, 이 논문은 한발 물러서서 '스폰서드 콘텐츠'라는 거래 대상 자체의 본질적 불확실성에 주목합니다. '인식론적 시장 객체'라는 개념은, 우리가 왜 인플루언서 마케팅의 가치를 명확히 측정하기 어려운지에 대한 근본적인 이유를 설명하는 강력한 분석 도구를 제공합니다. 이는 단순히 '측정 기술이 부족해서'가 아니라, '객체 자체가 사회적으로 합의된 의미와 가치를 형성해나가는 과정에 있기 때문'이라는 심도 깊은 통찰을 줍니다.\n\n2.  현 시대적 비즈니스 트렌드와의 연계성:\n    *   플랫폼 경제의 권력 역학 조명: 이 연구는 인스타그램, 틱톡, 유튜브와 같은 플랫폼이 단순한 중개자를 넘어, 가치 평가의 규칙을 만들고 데이터 비대칭성을 통해 시장 권력을 행사하는 방식을 명확히 보여줍니다. 이는 브랜드-크리에이터의 이자(dyadic) 관계를 넘어선 플랫폼 중심의 생태계적 관점을 제시합니다.\n    *   '긱 이코노미(Gig Economy)'의 심화된 논의: 크리에이터를 일종의 독립적인 '긱 워커(gig worker)'로 볼 때, 이 논문은 그들이 겪는 가치 평가의 불안정성과 브랜드와의 권력 불균형 문제를 심층적으로 다룹니다. 이는 크리에이터라는 새로운 직업의 노동 조건과 시장 구조를 이해하는 데 중요한 시사점을 제공합니다.\n\n3.  미래 지향적 확장 가능성: 저자들이 직접 언급했듯이, 이 연구의 가장 큰 공헌 중 하나는 그 분석 틀의 확장성입니다. 현재 비즈니스 세계의 최대 화두인 생성형 AI(Generative AI), 메타버스(Metaverse) 내 자산, NFT 등은 모두 '인식론적 시장 객체'의 특성을 강하게 띱니다. 이들의 가치는 무엇이며, 어떻게 거래되어야 하고, 누가 그 가치를 통제할 것인지에 대한 사회적 합의가 아직 이루어지지 않았습니다. 이 논문은 이러한 미래 시장의 혼란과 갈등, 그리고 새로운 질서 형성 과정을 예측하고 분석하는 데 매우 유용한 이론적 기반이 될 것입니다.\n\n결론적으로, 이 논문은 급변하는 디지털 시장의 복잡성을 설명하기 위해 새로운 이론적 무기를 장착해주었다는 점에서 단순한 현상 분석을 넘어선 패러다임 전환적 연구로 평가될 수 있습니다.\n\n### C. 저자 백그라운드:\n\n이 논문의 저자들은 주로 소비자 문화 이론(Consumer Culture Theory, CCT) 분야에서 활동하는 저명한 학자들로, 이들의 배경은 논문의 질적이고 해석적인 접근 방식을 잘 설명해 줍니다.\n\n1.  제이넵 아르셀 (Zeynep Arsel):\n    *   주요 연구 분야: 소비자 문화 이론(CCT) 분야의 세계적인 석학 중 한 명입니다. 특히 소비자의 '취향(taste)'이 어떻게 사회적으로 형성되고 변화하는지, 시장과 문화가 어떻게 상호작용하는지에 대한 연구로 명성이 높습니다. 마켓플레이스, 디지털 소비, 미디어 등을 문화적 관점에서 분석하는 데 탁월합니다.\n    *   학력 및 배경: 위스콘신-매디슨 대학교(University of Wisconsin-Madison)에서 마케팅 박사 학위를 받았으며, 그의 지도교수는 CCT 분야의 창시자 중 한 명인 크레이그 톰슨(Craig J. Thompson)입니다. 이는 그녀가 CCT 학계의 핵심 계보에 속해 있음을 의미합니다. 현재 캐나다 콩코디아 대학교(Concordia University) 존 몰슨 경영대학(John Molson School of Business)의 교수로 재직 중입니다.\n    *   연구 성향: 그녀의 연구는 정량적 분석보다는 인터뷰, 텍스트 분석, 민족지학적 연구(ethnography) 등 질적 연구 방법론에 기반하여 시장 현상의 심층적인 의미를 파헤치는 특징이 있습니다. 이 논문 역시 이러한 연구 성향이 그대로 반영되어 있습니다.\n\n2.  마리아 캐롤라이나 자네트 (Maria Carolina Zanette):\n    *   주요 연구 분야: 제이넵 아르셀 교수와 긴밀하게 협업하는 연구자로, 그녀 역시 소비자 문화 이론, 시장 형성 과정(market-making), 디지털 소비문화, 기업가정신(entrepreneurship) 등을 연구합니다. 특히 새로운 시장이 어떻게 만들어지고 안정화되는지에 관심이 많습니다.\n    *   학력 및 배경: 브라질 출신 학자로, 현재 영국 요크 대학교(University of York) 경영대학원 교수로 재직 중입니다. 제이넵 아르셀 교수와의 지속적인 공동 연구를 통해 CCT 학계에서 입지를 다지고 있습니다.\n\n3.  캐롤라이나 다 호샤 멜루 (Carolina da Rocha Melo):\n    *   주요 연구 분야 및 배경: 앞선 두 저자에 비해 상대적으로 신진 연구자일 가능성이 높습니다. 이름에서 유추할 수 있듯이 브라질/포르투갈어권 배경의 학자로 추정됩니다. 제이넵 아르셀, 마리아 자네트와 같은 CCT 분야의 대가들과 함께 탑 저널에 논문을 게재했다는 것은, 그녀 역시 동일한 학문적 전통(CCT) 안에서 훈련받았거나 연구를 수행하고 있음을 시사합니다. 아마도 박사 과정생이었거나 박사 후 연구원으로서 연구에 참여했을 가능성이 있으며, 디지털 플랫폼과 크리에이터 경제에 대한 깊은 이해를 바탕으로 연구에 기여했을 것으로 보입니다.\n\n종합적 분석: 이 저자 구성은 CCT라는 강력한 이론적 기반을 가진 시니어 학자(Arsel)와, 이를 새로운 디지털 현상에 적용하고 확장하는 데 능숙한 협력 연구자(Zanette, Melo)들의 이상적인 조합을 보여줍니다. 따라서 이 논문이 단순한 현상 기술을 넘어 '인식론적 시장 객체'라는 정교한 이론적 개념을 제시할 수 있었던 것은 저자들의 이러한 깊이 있는 학문적 배경 덕분이라고 할 수 있습니다.",
      "analysis_en": "네, 세계적인 마케팅 학술 연구 보조 AI로서 요청하신 논문에 대한 심층 분석을 시작하겠습니다.\n\n---\n\n### A. 논문 요약:\n\n이 논문은 브랜드와 크리에이터(인플루언서) 간의 파트너십을 통해 제작되는 '스폰서드 콘텐츠(sponsored content)'가 현대 디지털 마케팅 시장에서 어떻게 이해되고 거래되는지를 분석합니다. 저자들은 스폰서드 콘텐츠가 브랜드, 크리에이터, 그리고 이를 중개하는 플랫폼 모두에게 그 가치와 제작 방식이 명확하게 이해되지 않는다는 점에 주목합니다.\n\n이러한 불완전한 이해 상태를 설명하기 위해, 저자들은 스폰서드 콘텐츠를 '인식론적 시장 객체(epistemic market object)'라는 새로운 개념으로 정의합니다. 이는 \"마케팅 기능을 수행하지만, 그것을 사용하는 시장 참여자들이 부분적으로만 이해하고 있는 객체\"를 의미합니다. 즉, 스폰서드 콘텐츠의 '진짜 가치'가 무엇인지, '어떻게 만들어야 가장 효과적인지'에 대한 명확한 합의나 표준이 부재한 상태라는 것입니다.\n\n이로 인해 시장에서는 두 가지 핵심적인 모호성(ambiguity)이 발생합니다:\n1.  가치 평가의 모호성(Valuation Ambiguity): 스폰서드 콘텐츠의 가격을 어떻게 책정해야 하는가? (예: 팔로워 수, 조회수, 참여율, 진정성 등 어떤 기준으로 가치를 매길 것인가?)\n2.  공동 제작의 모호성(Coproduction Ambiguity): 브랜드의 상업적 메시지와 크리에이터의 창의적 자율성 사이에서 어떻게 균형을 맞춰 콘텐츠를 제작해야 하는가?\n\n연구 결과, 브랜드, 크리에이터, 중개 에이전시 등 시장 참여자들은 이러한 모호성을 해결하기 위해 끊임없이 지식을 만들고 적용하려 노력하지만, 이 과정은 불완전하며 각자의 이해관계에 따라 다르게 진행됩니다. 결과적으로 이는 참여자 간의 가치 분배와 권력 관계에서 비대칭성(asymmetry)을 낳게 됩니다. 예를 들어, 데이터를 더 많이 가진 플랫폼이나 브랜드가 협상에서 우위를 점하거나, 유명 크리에이터가 브랜드에 더 큰 영향력을 행사하는 현상이 나타납니다.\n\n결론적으로, 이 논문은 스폰서드 콘텐츠와 같은 '인식론적 시장 객체'가 기존 시장의 역할(브랜드, 광고대행사, 소비자)과 관계를 어떻게 파괴하고 재편하는지를 보여주며, 이러한 분석 틀이 향후 생성형 AI, 메타버스, NFT 등 새롭게 등장하는 다른 시장 객체를 이해하는 데에도 유용하게 적용될 수 있음을 시사합니다.\n\n### B. 연구적 의의:\n\n이 논문은 기존 연구나 논리를 단순히 반박하기보다는, 현대 마케팅의 가장 역동적인 영역인 크리에이터 이코노미(Creator Economy)를 분석하는 새로운 이론적 패러다임을 제시한다는 점에서 큰 의의를 가집니다.\n\n1.  새로운 개념적 렌즈 제시: 기존의 인플루언서 마케팅 연구가 주로 효과성 측정(ROI), 진정성(authenticity), 소비자 반응 등에 집중했다면, 이 논문은 한발 물러서서 '스폰서드 콘텐츠'라는 거래 대상 자체의 본질적 불확실성에 주목합니다. '인식론적 시장 객체'라는 개념은, 우리가 왜 인플루언서 마케팅의 가치를 명확히 측정하기 어려운지에 대한 근본적인 이유를 설명하는 강력한 분석 도구를 제공합니다. 이는 단순히 '측정 기술이 부족해서'가 아니라, '객체 자체가 사회적으로 합의된 의미와 가치를 형성해나가는 과정에 있기 때문'이라는 심도 깊은 통찰을 줍니다.\n\n2.  현 시대적 비즈니스 트렌드와의 연계성:\n    *   플랫폼 경제의 권력 역학 조명: 이 연구는 인스타그램, 틱톡, 유튜브와 같은 플랫폼이 단순한 중개자를 넘어, 가치 평가의 규칙을 만들고 데이터 비대칭성을 통해 시장 권력을 행사하는 방식을 명확히 보여줍니다. 이는 브랜드-크리에이터의 이자(dyadic) 관계를 넘어선 플랫폼 중심의 생태계적 관점을 제시합니다.\n    *   '긱 이코노미(Gig Economy)'의 심화된 논의: 크리에이터를 일종의 독립적인 '긱 워커(gig worker)'로 볼 때, 이 논문은 그들이 겪는 가치 평가의 불안정성과 브랜드와의 권력 불균형 문제를 심층적으로 다룹니다. 이는 크리에이터라는 새로운 직업의 노동 조건과 시장 구조를 이해하는 데 중요한 시사점을 제공합니다.\n\n3.  미래 지향적 확장 가능성: 저자들이 직접 언급했듯이, 이 연구의 가장 큰 공헌 중 하나는 그 분석 틀의 확장성입니다. 현재 비즈니스 세계의 최대 화두인 생성형 AI(Generative AI), 메타버스(Metaverse) 내 자산, NFT 등은 모두 '인식론적 시장 객체'의 특성을 강하게 띱니다. 이들의 가치는 무엇이며, 어떻게 거래되어야 하고, 누가 그 가치를 통제할 것인지에 대한 사회적 합의가 아직 이루어지지 않았습니다. 이 논문은 이러한 미래 시장의 혼란과 갈등, 그리고 새로운 질서 형성 과정을 예측하고 분석하는 데 매우 유용한 이론적 기반이 될 것입니다.\n\n결론적으로, 이 논문은 급변하는 디지털 시장의 복잡성을 설명하기 위해 새로운 이론적 무기를 장착해주었다는 점에서 단순한 현상 분석을 넘어선 패러다임 전환적 연구로 평가될 수 있습니다.\n\n### C. 저자 백그라운드:\n\n이 논문의 저자들은 주로 소비자 문화 이론(Consumer Culture Theory, CCT) 분야에서 활동하는 저명한 학자들로, 이들의 배경은 논문의 질적이고 해석적인 접근 방식을 잘 설명해 줍니다.\n\n1.  제이넵 아르셀 (Zeynep Arsel):\n    *   주요 연구 분야: 소비자 문화 이론(CCT) 분야의 세계적인 석학 중 한 명입니다. 특히 소비자의 '취향(taste)'이 어떻게 사회적으로 형성되고 변화하는지, 시장과 문화가 어떻게 상호작용하는지에 대한 연구로 명성이 높습니다. 마켓플레이스, 디지털 소비, 미디어 등을 문화적 관점에서 분석하는 데 탁월합니다.\n    *   학력 및 배경: 위스콘신-매디슨 대학교(University of Wisconsin-Madison)에서 마케팅 박사 학위를 받았으며, 그의 지도교수는 CCT 분야의 창시자 중 한 명인 크레이그 톰슨(Craig J. Thompson)입니다. 이는 그녀가 CCT 학계의 핵심 계보에 속해 있음을 의미합니다. 현재 캐나다 콩코디아 대학교(Concordia University) 존 몰슨 경영대학(John Molson School of Business)의 교수로 재직 중입니다.\n    *   연구 성향: 그녀의 연구는 정량적 분석보다는 인터뷰, 텍스트 분석, 민족지학적 연구(ethnography) 등 질적 연구 방법론에 기반하여 시장 현상의 심층적인 의미를 파헤치는 특징이 있습니다. 이 논문 역시 이러한 연구 성향이 그대로 반영되어 있습니다.\n\n2.  마리아 캐롤라이나 자네트 (Maria Carolina Zanette):\n    *   주요 연구 분야: 제이넵 아르셀 교수와 긴밀하게 협업하는 연구자로, 그녀 역시 소비자 문화 이론, 시장 형성 과정(market-making), 디지털 소비문화, 기업가정신(entrepreneurship) 등을 연구합니다. 특히 새로운 시장이 어떻게 만들어지고 안정화되는지에 관심이 많습니다.\n    *   학력 및 배경: 브라질 출신 학자로, 현재 영국 요크 대학교(University of York) 경영대학원 교수로 재직 중입니다. 제이넵 아르셀 교수와의 지속적인 공동 연구를 통해 CCT 학계에서 입지를 다지고 있습니다.\n\n3.  캐롤라이나 다 호샤 멜루 (Carolina da Rocha Melo):\n    *   주요 연구 분야 및 배경: 앞선 두 저자에 비해 상대적으로 신진 연구자일 가능성이 높습니다. 이름에서 유추할 수 있듯이 브라질/포르투갈어권 배경의 학자로 추정됩니다. 제이넵 아르셀, 마리아 자네트와 같은 CCT 분야의 대가들과 함께 탑 저널에 논문을 게재했다는 것은, 그녀 역시 동일한 학문적 전통(CCT) 안에서 훈련받았거나 연구를 수행하고 있음을 시사합니다. 아마도 박사 과정생이었거나 박사 후 연구원으로서 연구에 참여했을 가능성이 있으며, 디지털 플랫폼과 크리에이터 경제에 대한 깊은 이해를 바탕으로 연구에 기여했을 것으로 보입니다.\n\n종합적 분석: 이 저자 구성은 CCT라는 강력한 이론적 기반을 가진 시니어 학자(Arsel)와, 이를 새로운 디지털 현상에 적용하고 확장하는 데 능숙한 협력 연구자(Zanette, Melo)들의 이상적인 조합을 보여줍니다. 따라서 이 논문이 단순한 현상 기술을 넘어 '인식론적 시장 객체'라는 정교한 이론적 개념을 제시할 수 있었던 것은 저자들의 이러한 깊이 있는 학문적 배경 덕분이라고 할 수 있습니다."
    },
    {
      "slug": "the-golden-halo-of-defaults-in-simple-choices",
      "title": "The Golden Halo of Defaults in Simple Choices",
      "authors": "Nicolette J. Sullivan, Alexander Breslav, Samyukta S. Doré, Matthew D. Bachman, Scott A. Huettel",
      "journal": "Journal of Marketing Research",
      "date": "2025-2-11",
      "url": "https://doi.org/10.1177/00222437241303738",
      "abstract": "Defaults are pervasive in consumer choice. The authors combine eye-tracking laboratory experiments with cognitive modeling to pinpoint the influence of defaults in the decision process and conduct naturalistic experiments with large preregistered samples to test the limits of defaults on consumer choices. Contrary to previous assumptions, in simple binary choices, default options did not potentiate rapid heuristic-based decisions but instead altered processes of attention and valuation. Model comparison indicated that defaults received a positive boost in value—a “golden halo”—that was large enough to increase hedonic choices when the default was hedonic, but had limited effects for utilitarian defaults or for when defaults were incongruent with background goals. The findings illustrate and quantify the mechanisms through which default options shape subsequent decisions in simple choices. Further, the authors establish boundary conditions for when defaults can and cannot be used to nudge consumer choice.",
      "analysis_ko": "알겠습니다. 세계적인 마케팅 학술 연구 보조 AI로서, 요청하신 Journal of Marketing Research(JMR) 논문, \"The Golden Halo of Defaults in Simple Choices\"에 대해 심층 분석을 제공하겠습니다.\n\n### A. 논문 요약:\n\n이 논문은 소비자의 선택 과정에서 '디폴트(기본값)' 옵션이 어떻게 영향을 미치는지 그 심리적 메커니즘을 규명한 연구입니다. 저자들은 아이트래킹(eye-tracking)을 활용한 실험실 연구와 인지 모델링, 그리고 대규모 사전 등록 표본을 이용한 자연주의적 실험을 결합하여 디폴트의 효과를 분석했습니다.\n\n연구의 핵심 발견은 다음과 같습니다.\n\n1.  기존 통념의 반박: 이전까지 디폴트 효과는 소비자가 인지적 노력을 줄이려는 '휴리스틱(heuristic)' 또는 지름길 사고방식 때문에 발생한다고 여겨졌습니다. 하지만 이 연구는 단순한 이진 선택 상황에서 디폴트가 빠른 휴리스틱적 결정을 유도하는 것이 아니라, 소비자의 주의(attention)와 가치 평가(valuation) 과정 자체를 변화시킨다는 점을 밝혀냈습니다.\n2.  '골든 헤일로(Golden Halo)' 효과: 인지 모델링 분석 결과, 디폴트로 설정된 옵션은 그 자체로 긍정적인 가치가 더해지는, 즉 '황금 후광' 효과를 얻는 것으로 나타났습니다. 소비자는 디폴트 옵션을 무의식적으로 더 우수하거나 매력적인 것으로 인식하게 됩니다.\n3.  효과의 경계 조건(Boundary Conditions): 이 '골든 헤일로' 효과는 모든 상황에서 동일하게 나타나지 않았습니다.\n    *   디폴트 옵션이 쾌락적(hedonic) 상품일 경우, 그 효과가 뚜렷하게 나타나 선택 가능성을 높였습니다.\n    *   반면, 디폴트 옵션이 실용적(utilitarian) 상품이거나 소비자의 기저 목표(background goals)와 상충될 경우에는 그 효과가 제한적이었습니다.\n\n결론적으로, 이 논문은 디폴트가 단순한 '현상 유지 편향'을 넘어, 선택 옵션의 내재적 가치 평가를 직접적으로 바꾸는 심리적 메커니즘을 규명하고, 그 효과가 발휘되는 조건과 한계를 명확히 제시했다는 점에서 중요한 의의를 가집니다.\n\n### B. 연구적 의의:\n\n이 논문의 연구적 의의는 크게 세 가지 측면에서 분석할 수 있습니다.\n\n1.  기존 논리의 정교한 반박 및 심화:\n    이 연구는 디폴트 효과에 대한 기존의 지배적인 설명이었던 '인지적 구두쇠(cognitive miser)' 가설, 즉 인간은 생각하기를 싫어해 기본 설정을 따른다는 논리에 정면으로 도전합니다. 이는 기존 논리를 완전히 뒤집는 '패러다임 전환'이라기보다는, 현상을 더 깊은 차원에서 설명하는 '메커니즘의 규명과 정교화' 에 가깝습니다. \"왜 디폴트를 선택하는가?\"라는 질문에 '게으르기 때문'이라는 행동적 답변을 넘어, '디폴트 옵션 자체가 더 좋게 보이기 때문'이라는 인지적, 심리적 답변을 제시한 것입니다. 이는 행동경제학의 '넛지(Nudge)' 이론을 한 단계 발전시키는 중요한 학술적 기여입니다.\n\n2.  첨단 연구 방법론의 결합:\n    본 연구는 마케팅 학계의 최신 트렌드를 명확히 보여줍니다. 단순한 설문조사나 선택 실험(A/B 테스트)을 넘어, ① 아이트래킹으로 소비자의 실시간 주의 집중 과정을 포착하고, ② 인지 모델링으로 눈에 보이지 않는 가치 평가 과정을 수학적으로 추론하며, ③ 대규모 자연주의적 실험을 통해 연구 결과의 현실 타당성(generalizability)을 확보했습니다. 이처럼 여러 방법론을 결합하여 인간의 복잡한 의사결정 과정을 다각도로 분석하는 접근은 향후 소비자 행동 연구의 새로운 표준이 될 가능성이 높습니다.\n\n3.  현 시대 비즈니스 트렌드와의 연관성:\n    *   디지털 환경과 구독 경제: 오늘날 거의 모든 디지털 서비스(앱 권한 설정, 뉴스레터 구독, 소프트웨어 설치)와 구독 경제 모델은 디폴트 설정을 적극적으로 활용합니다. 이 연구는 기업들이 디폴트를 설계할 때 어떤 제품/서비스에 적용해야 가장 효과적인지에 대한 구체적인 가이드라인을 제공합니다. 예를 들어, 엔터테인먼트 OTT 서비스(쾌락재)의 프리미엄 요금제를 디폴트로 설정하는 것은 효과적일 수 있지만, 사무용 소프트웨어(실용재)의 부가 기능을 디폴트로 설정하는 것은 효과가 미미할 수 있음을 시사합니다.\n    *   개인화 마케팅의 정교화: '골든 헤일로' 효과가 소비자의 기저 목표와 연관이 있다는 점은 초개인화 마케팅에 중요한 함의를 줍니다. 고객의 현재 목표(예: 건강 증진, 비용 절약)를 파악하고 그에 부합하는 옵션을 디폴트로 제시할 때 '넛지'의 성공 확률이 극대화될 수 있음을 의미합니다.\n    *   마케팅 윤리 문제: 디폴트가 소비자의 가치 판단을 직접적으로 '왜곡'할 수 있다는 사실은 중요한 윤리적 문제를 제기합니다. 기업이 이 메커니즘을 악용하여 소비자에게 불필요하거나 더 비싼 옵션을 유도할 수 있기 때문입니다. 따라서 향후 관련 규제나 소비자 보호 정책을 수립하는 데 중요한 학술적 근거를 제공할 수 있습니다.\n\n### C. 저자 백그라운드:\n\n저자들의 배경을 분석해 보면, 이 연구가 왜 탄생할 수 있었는지 명확히 알 수 있습니다.\n\n*   Nicolette J. Sullivan (제1저자): 제1저자는 통상적으로 연구 아이디어를 내고 실험 설계, 데이터 분석 등 연구 전반을 주도한 핵심 연구자입니다. 그녀는 소비자 의사결정, 특히 선택 아키텍처(choice architecture)와 넛지가 행동에 미치는 영향을 연구하는 신진 학자일 가능성이 높습니다. 이 논문은 그녀의 박사학위 연구의 일부이거나, 박사 후 연구원으로서 수행한 주요 프로젝트일 것으로 추정됩니다.\n\n*   Scott A. Huettel (교신저자/마지막 저자): 마지막 저자는 보통 연구 그룹을 이끄는 시니어 교수(지도교수)입니다. Scott A. Huettel은 듀크 대학교(Duke University)의 저명한 심리학 및 신경과학 교수로, 의사결정 신경과학(Decision Neuroscience) 분야의 세계적인 권위자입니다. 그의 연구실은 fMRI, 아이트래킹 등 첨단 기술을 활용하여 인간의 선택, 가치 평가, 자기 통제와 관련된 뇌의 메커니즘을 연구합니다. 이 논문에서 사용된 아이트래킹과 인지 모델링 기법은 바로 그의 전문 분야에서 비롯된 것입니다.\n\n*   Alexander Breslav, Samyukta S. Doré, Matthew D. Bachman (공동저자): 이들은 Huettel 교수의 연구실에 소속된 동료 박사과정생, 박사 후 연구원, 혹은 협력 연구자일 가능성이 매우 높습니다. 이들은 각각 데이터 분석, 실험 진행, 모델링 등 특정 전문 분야에서 연구에 기여했을 것입니다.\n\n*   종합적 분석: 이 저자 구성은 신경과학/인지심리학과 마케팅의 성공적인 융합 연구라는 점을 명확히 보여줍니다. 마케팅 분야의 현상(디폴트 효과)을 신경과학의 정교한 방법론으로 파헤친 것입니다. 즉, 마케팅 연구자가 \"소비자들은 왜 디폴트를 선택할까?\"라는 질문을 던지면, 의사결정 신경과학자인 Huettel 교수가 \"그 답을 찾기 위해 그들의 뇌와 눈이 어떻게 작동하는지 들여다보자\"라고 접근하는 방식의 협업입니다. 이러한 학제 간 융합은 최근 마케팅 최상위 저널에서 두드러지는 트렌드이며, 인간의 '블랙박스'와 같았던 의사결정 과정을 과학적으로 규명하려는 학계의 노력을 상징합니다.",
      "analysis_en": "알겠습니다. 세계적인 마케팅 학술 연구 보조 AI로서, 요청하신 Journal of Marketing Research(JMR) 논문, \"The Golden Halo of Defaults in Simple Choices\"에 대해 심층 분석을 제공하겠습니다.\n\n### A. 논문 요약:\n\n이 논문은 소비자의 선택 과정에서 '디폴트(기본값)' 옵션이 어떻게 영향을 미치는지 그 심리적 메커니즘을 규명한 연구입니다. 저자들은 아이트래킹(eye-tracking)을 활용한 실험실 연구와 인지 모델링, 그리고 대규모 사전 등록 표본을 이용한 자연주의적 실험을 결합하여 디폴트의 효과를 분석했습니다.\n\n연구의 핵심 발견은 다음과 같습니다.\n\n1.  기존 통념의 반박: 이전까지 디폴트 효과는 소비자가 인지적 노력을 줄이려는 '휴리스틱(heuristic)' 또는 지름길 사고방식 때문에 발생한다고 여겨졌습니다. 하지만 이 연구는 단순한 이진 선택 상황에서 디폴트가 빠른 휴리스틱적 결정을 유도하는 것이 아니라, 소비자의 주의(attention)와 가치 평가(valuation) 과정 자체를 변화시킨다는 점을 밝혀냈습니다.\n2.  '골든 헤일로(Golden Halo)' 효과: 인지 모델링 분석 결과, 디폴트로 설정된 옵션은 그 자체로 긍정적인 가치가 더해지는, 즉 '황금 후광' 효과를 얻는 것으로 나타났습니다. 소비자는 디폴트 옵션을 무의식적으로 더 우수하거나 매력적인 것으로 인식하게 됩니다.\n3.  효과의 경계 조건(Boundary Conditions): 이 '골든 헤일로' 효과는 모든 상황에서 동일하게 나타나지 않았습니다.\n    *   디폴트 옵션이 쾌락적(hedonic) 상품일 경우, 그 효과가 뚜렷하게 나타나 선택 가능성을 높였습니다.\n    *   반면, 디폴트 옵션이 실용적(utilitarian) 상품이거나 소비자의 기저 목표(background goals)와 상충될 경우에는 그 효과가 제한적이었습니다.\n\n결론적으로, 이 논문은 디폴트가 단순한 '현상 유지 편향'을 넘어, 선택 옵션의 내재적 가치 평가를 직접적으로 바꾸는 심리적 메커니즘을 규명하고, 그 효과가 발휘되는 조건과 한계를 명확히 제시했다는 점에서 중요한 의의를 가집니다.\n\n### B. 연구적 의의:\n\n이 논문의 연구적 의의는 크게 세 가지 측면에서 분석할 수 있습니다.\n\n1.  기존 논리의 정교한 반박 및 심화:\n    이 연구는 디폴트 효과에 대한 기존의 지배적인 설명이었던 '인지적 구두쇠(cognitive miser)' 가설, 즉 인간은 생각하기를 싫어해 기본 설정을 따른다는 논리에 정면으로 도전합니다. 이는 기존 논리를 완전히 뒤집는 '패러다임 전환'이라기보다는, 현상을 더 깊은 차원에서 설명하는 '메커니즘의 규명과 정교화' 에 가깝습니다. \"왜 디폴트를 선택하는가?\"라는 질문에 '게으르기 때문'이라는 행동적 답변을 넘어, '디폴트 옵션 자체가 더 좋게 보이기 때문'이라는 인지적, 심리적 답변을 제시한 것입니다. 이는 행동경제학의 '넛지(Nudge)' 이론을 한 단계 발전시키는 중요한 학술적 기여입니다.\n\n2.  첨단 연구 방법론의 결합:\n    본 연구는 마케팅 학계의 최신 트렌드를 명확히 보여줍니다. 단순한 설문조사나 선택 실험(A/B 테스트)을 넘어, ① 아이트래킹으로 소비자의 실시간 주의 집중 과정을 포착하고, ② 인지 모델링으로 눈에 보이지 않는 가치 평가 과정을 수학적으로 추론하며, ③ 대규모 자연주의적 실험을 통해 연구 결과의 현실 타당성(generalizability)을 확보했습니다. 이처럼 여러 방법론을 결합하여 인간의 복잡한 의사결정 과정을 다각도로 분석하는 접근은 향후 소비자 행동 연구의 새로운 표준이 될 가능성이 높습니다.\n\n3.  현 시대 비즈니스 트렌드와의 연관성:\n    *   디지털 환경과 구독 경제: 오늘날 거의 모든 디지털 서비스(앱 권한 설정, 뉴스레터 구독, 소프트웨어 설치)와 구독 경제 모델은 디폴트 설정을 적극적으로 활용합니다. 이 연구는 기업들이 디폴트를 설계할 때 어떤 제품/서비스에 적용해야 가장 효과적인지에 대한 구체적인 가이드라인을 제공합니다. 예를 들어, 엔터테인먼트 OTT 서비스(쾌락재)의 프리미엄 요금제를 디폴트로 설정하는 것은 효과적일 수 있지만, 사무용 소프트웨어(실용재)의 부가 기능을 디폴트로 설정하는 것은 효과가 미미할 수 있음을 시사합니다.\n    *   개인화 마케팅의 정교화: '골든 헤일로' 효과가 소비자의 기저 목표와 연관이 있다는 점은 초개인화 마케팅에 중요한 함의를 줍니다. 고객의 현재 목표(예: 건강 증진, 비용 절약)를 파악하고 그에 부합하는 옵션을 디폴트로 제시할 때 '넛지'의 성공 확률이 극대화될 수 있음을 의미합니다.\n    *   마케팅 윤리 문제: 디폴트가 소비자의 가치 판단을 직접적으로 '왜곡'할 수 있다는 사실은 중요한 윤리적 문제를 제기합니다. 기업이 이 메커니즘을 악용하여 소비자에게 불필요하거나 더 비싼 옵션을 유도할 수 있기 때문입니다. 따라서 향후 관련 규제나 소비자 보호 정책을 수립하는 데 중요한 학술적 근거를 제공할 수 있습니다.\n\n### C. 저자 백그라운드:\n\n저자들의 배경을 분석해 보면, 이 연구가 왜 탄생할 수 있었는지 명확히 알 수 있습니다.\n\n*   Nicolette J. Sullivan (제1저자): 제1저자는 통상적으로 연구 아이디어를 내고 실험 설계, 데이터 분석 등 연구 전반을 주도한 핵심 연구자입니다. 그녀는 소비자 의사결정, 특히 선택 아키텍처(choice architecture)와 넛지가 행동에 미치는 영향을 연구하는 신진 학자일 가능성이 높습니다. 이 논문은 그녀의 박사학위 연구의 일부이거나, 박사 후 연구원으로서 수행한 주요 프로젝트일 것으로 추정됩니다.\n\n*   Scott A. Huettel (교신저자/마지막 저자): 마지막 저자는 보통 연구 그룹을 이끄는 시니어 교수(지도교수)입니다. Scott A. Huettel은 듀크 대학교(Duke University)의 저명한 심리학 및 신경과학 교수로, 의사결정 신경과학(Decision Neuroscience) 분야의 세계적인 권위자입니다. 그의 연구실은 fMRI, 아이트래킹 등 첨단 기술을 활용하여 인간의 선택, 가치 평가, 자기 통제와 관련된 뇌의 메커니즘을 연구합니다. 이 논문에서 사용된 아이트래킹과 인지 모델링 기법은 바로 그의 전문 분야에서 비롯된 것입니다.\n\n*   Alexander Breslav, Samyukta S. Doré, Matthew D. Bachman (공동저자): 이들은 Huettel 교수의 연구실에 소속된 동료 박사과정생, 박사 후 연구원, 혹은 협력 연구자일 가능성이 매우 높습니다. 이들은 각각 데이터 분석, 실험 진행, 모델링 등 특정 전문 분야에서 연구에 기여했을 것입니다.\n\n*   종합적 분석: 이 저자 구성은 신경과학/인지심리학과 마케팅의 성공적인 융합 연구라는 점을 명확히 보여줍니다. 마케팅 분야의 현상(디폴트 효과)을 신경과학의 정교한 방법론으로 파헤친 것입니다. 즉, 마케팅 연구자가 \"소비자들은 왜 디폴트를 선택할까?\"라는 질문을 던지면, 의사결정 신경과학자인 Huettel 교수가 \"그 답을 찾기 위해 그들의 뇌와 눈이 어떻게 작동하는지 들여다보자\"라고 접근하는 방식의 협업입니다. 이러한 학제 간 융합은 최근 마케팅 최상위 저널에서 두드러지는 트렌드이며, 인간의 '블랙박스'와 같았던 의사결정 과정을 과학적으로 규명하려는 학계의 노력을 상징합니다."
    },
    {
      "slug": "the-last-hurrah-effect-end-of-period-temporal-landmarks-increase-optimism-and-fi",
      "title": "The Last Hurrah Effect: End-of-Period Temporal Landmarks Increase Optimism and Financial Risk-Taking",
      "authors": "Avni M. Shah, Xinlong Li",
      "journal": "Journal of Marketing Research",
      "date": "2025-2-10",
      "url": "https://doi.org/10.1177/00222437241286785",
      "abstract": "Understanding what drives risk-taking is fundamental for the study of choice under uncertainty. One widely discussed question is when and why people engage in risk-taking. Prior work finds evidence for an ending effect, where risk-taking increases on the last gamble in a series when outcomes are immediately realized. The authors test whether socially ubiquitous end-of-period temporal landmarks (e.g., last day of the work week, month, year) alter financial risk-taking even when outcomes are not immediate. Using data from a large peer-to-peer investment platform in the United States, they show that investors make riskier financial investment decisions on Fridays relative to those made earlier in the week. Consistent with a broader end-of-period effect, risk-taking also increases on the last day of the month, on the last day of the year, and on weekdays prior to a long weekend. Follow-up lab experiments identify a novel mechanism driving ending effects: As people near the end of a temporal period, they feel more optimistic that their financial risks will pay off, driving greater financial risk-taking. The shift in risk-taking is not without consequence: In this specific peer-to-peer context, the authors show that end-of-period investments perform worse over time, losing money relative to investments made on other days.",
      "analysis_ko": "네, 세계적인 마케팅 학술 연구 보조 AI로서 요청하신 논문에 대한 심층 분석을 시작하겠습니다.\n\n---\n\n### A. 논문 요약:\n\n이 논문은 \"마지막 한탕 효과(The Last Hurrah Effect)\"라는 새로운 개념을 제시하며, 사람들이 특정 기간의 끝(예: 금요일, 월말, 연말)에 가까워질수록 더 낙관적이 되어 재무적으로 더 위험한 의사결정을 내리는 경향이 있음을 실증적으로 규명한 연구입니다.\n\n연구진은 미국의 대규모 P2P(Peer-to-Peer) 투자 플랫폼 데이터를 분석하여, 투자자들이 주초(월-목)에 비해 금요일에 더 위험도가 높은 대출에 투자하는 경향을 발견했습니다. 이러한 현상은 월말, 연말, 그리고 긴 주말 직전의 평일에도 동일하게 나타났습니다. 이는 단순히 특정 과업의 마지막 순서에서 나타나는 '종료 효과(ending effect)'를 넘어, 사회적으로 통용되는 '시간적 경계(temporal landmark)'가 투자 심리와 행동에 미치는 영향을 보여줍니다.\n\n이 효과의 심리적 원인을 파악하기 위해 연구진은 실험실 연구를 진행했습니다. 그 결과, 기간의 끝에 다다른 사람들은 자신의 재무적 리스크가 좋은 결과로 이어질 것이라는 '낙관주의(optimism)'가 증가하며, 이것이 위험 감수 행동을 촉진하는 핵심 기제임을 밝혀냈습니다. 중요한 점은, 이러한 낙관에 기반한 '마지막 한탕' 투자가 실제로는 다른 날에 이루어진 투자에 비해 장기적으로 더 낮은 성과를 보이며 금전적 손실로 이어진다는 사실입니다. 즉, 심리적 편향이 실질적인 재무적 손실을 야기할 수 있음을 보여줍니다.\n\n### B. 연구적 의의:\n\n이 논문은 기존 연구를 반박하기보다는, 고전적인 '종료 효과(ending effect)' 이론을 사회적으로 훨씬 더 보편적이고 중요한 맥락으로 확장하고 정교화했다는 점에서 큰 연구적 의의를 가집니다.\n\n1.  새로운 패러다임의 제시: '과업의 끝'에서 '시간의 끝'으로\n    *   기존의 종료 효과 연구는 주로 실험실 환경에서 '연속된 도박의 마지막 판'과 같이 명확하게 정의된 과업의 끝에서 위험 선호가 증가하는 현상에 집중했습니다. 이는 즉각적인 결과 확인이 가능한 제한된 상황에 국한되는 한계가 있었습니다.\n    *   본 연구는 이러한 개념을 '금요일', '월말' 등 사회적으로 공유되는 주기적인 시간의 경계로 확장했습니다. 이는 결과가 즉각적으로 나타나지 않는 '투자'와 같은 장기적 의사결정에도 심리적 마감 효과가 강력하게 작용함을 보여준 최초의 연구 중 하나입니다. 이는 불확실성 하에서의 선택(choice under uncertainty) 연구에 새로운 관점을 제시합니다.\n\n2.  새로운 심리적 기제(Mechanism) 규명: '손실 회피'가 아닌 '낙관주의'\n    *   기간의 끝에 위험을 감수하는 이유가 '이번 주(혹은 이번 달)의 손실을 만회하려는 마지막 시도'일 것이라는 직관적인 추측과 달리, 이 연구는 '미래에 대한 긍정적 기대감과 낙관주의'가 핵심 동인임을 실험을 통해 밝혔습니다. 즉, 사람들은 \"주말을 앞두고 있으니, 이번 투자는 잘 될 거야!\"와 같은 긍정적 감정에 휩싸여 더 과감한 결정을 내린다는 것입니다. 이는 리스크 의사결정의 감정적, 인지적 요인을 이해하는 데 중요한 기여를 합니다.\n\n3.  현 시대적 상황 및 비즈니스 트렌드와의 연관성\n    *   핀테크(FinTech) 및 디지털 금융 시대의 중요성: 이 연구는 P2P 플랫폼이라는 최신 금융 환경의 실제 데이터를 활용했습니다. 이는 로보어드바이저, 주식 거래 앱 등 개인의 비대면 금융 투자가 보편화된 오늘날 매우 중요한 시사점을 가집니다. 플랫폼 사업자들은 금요일 오후나 월말에 리스크가 높은 상품을 추천하는 마케팅을 강화할 수도 있고, 반대로 투자자 보호를 위해 \"기간의 마지막 날에는 평소보다 과감한 투자를 할 경향이 있습니다. 신중하게 결정하세요.\"와 같은 '넛지(nudge)'를 제공할 수도 있습니다.\n    *   소비자 보호 및 금융 정책: 이 연구는 심리적 편향이 실제 재무적 손실로 이어진다는 것을 명확히 보여줍니다. 이는 금융 감독 기관이나 소비자 보호 단체가 투자자 교육 프로그램을 설계할 때 '시간'이라는 변수가 의사결정에 미치는 영향을 포함해야 함을 시사합니다.\n    *   마케팅 전략에의 활용: 고위험-고수익 상품(예: 암호화폐, 신흥 시장 펀드)을 판매하는 기업은 잠재 고객의 '마지막 한탕 심리'가 극대화되는 금요일이나 월말에 집중적으로 광고나 프로모션을 집행하는 전략을 고려할 수 있습니다.\n\n### C. 저자 백그라운드:\n\n1.  Avni M. Shah (아브니 M. 샤)\n    *   주요 연구 분야: 샤 교수는 행동경제학을 기반으로 한 소비자 금융 의사결정 분야의 세계적인 석학입니다. 특히 돈의 심리학(psychology of money), 지불 방식(payment method)이 소비와 기부에 미치는 영향, 재무적 웰빙(financial well-being) 등을 깊이 있게 연구해 왔습니다. \"현금 없는 사회(cashless society)\"에서 소비자들이 겪는 심리적 변화에 대한 연구로도 유명합니다.\n    *   학력 및 배경: 듀크 대학교(Duke University)에서 마케팅 박사 학위를 받았으며, 이곳은 행동경제학의 대가인 댄 애리얼리(Dan Ariely) 교수가 재직했던 곳으로 행동과학 연구의 세계적인 중심지입니다. 이러한 학문적 배경은 그녀의 연구가 인간의 비합리성과 심리적 편향에 깊이 뿌리내리고 있음을 시사합니다. 현재는 토론토 대학교 로트만 경영대학(University of Toronto, Rotman School of Management)의 마케팅 교수로 재직 중입니다.\n    *   학문적 성향: 그녀의 연구는 실험실에서의 엄격한 인과관계 규명과 실제 현장에서의 대규모 데이터 분석을 결합하여 이론적 깊이와 현실적 적용 가능성을 동시에 추구하는 특징을 보입니다.\n\n2.  Xinlong Li (신롱 리)\n    *   주요 연구 분야: 리 교수는 소비자 재무 의사결정, 행동경제학, 디지털 마케팅, 베이지안 통계 모델링 등을 주로 연구하는 신진 학자입니다. 특히 소비자들이 언제, 왜 재무적으로 어려움을 겪는지에 대한 심리적, 환경적 요인을 탐구하는 데 관심이 많습니다.\n    *   학력 및 배경: 토론토 대학교 로트만 경영대학에서 마케팅 박사 학위를 받았습니다. 이를 통해 아브니 샤 교수가 그의 박사과정 지도교수였을 가능성이 매우 높다고 유추할 수 있습니다. 학계에서는 저명한 지도교수와 그의 제자가 함께 연구를 발전시켜 탑 저널에 논문을 게재하는 것이 일반적인 엘리트 코스입니다. 현재는 코네티컷 대학교 경영대학(University of Connecticut, School of Business)의 마케팅 조교수로 재직 중입니다.\n    *   학문적 성향: 지도교수인 샤 교수의 연구 흐름을 이어받아, 행동과학적 접근법과 최신 계량 분석 기법을 결합하여 복잡한 소비자 행동의 원인을 규명하는 데 강점을 보일 것으로 추정됩니다. 이 논문에서 P2P 데이터라는 대규모 필드 데이터를 분석한 것은 그의 계량적 분석 능력을 보여주는 부분이기도 합니다.",
      "analysis_en": "네, 세계적인 마케팅 학술 연구 보조 AI로서 요청하신 논문에 대한 심층 분석을 시작하겠습니다.\n\n---\n\n### A. 논문 요약:\n\n이 논문은 \"마지막 한탕 효과(The Last Hurrah Effect)\"라는 새로운 개념을 제시하며, 사람들이 특정 기간의 끝(예: 금요일, 월말, 연말)에 가까워질수록 더 낙관적이 되어 재무적으로 더 위험한 의사결정을 내리는 경향이 있음을 실증적으로 규명한 연구입니다.\n\n연구진은 미국의 대규모 P2P(Peer-to-Peer) 투자 플랫폼 데이터를 분석하여, 투자자들이 주초(월-목)에 비해 금요일에 더 위험도가 높은 대출에 투자하는 경향을 발견했습니다. 이러한 현상은 월말, 연말, 그리고 긴 주말 직전의 평일에도 동일하게 나타났습니다. 이는 단순히 특정 과업의 마지막 순서에서 나타나는 '종료 효과(ending effect)'를 넘어, 사회적으로 통용되는 '시간적 경계(temporal landmark)'가 투자 심리와 행동에 미치는 영향을 보여줍니다.\n\n이 효과의 심리적 원인을 파악하기 위해 연구진은 실험실 연구를 진행했습니다. 그 결과, 기간의 끝에 다다른 사람들은 자신의 재무적 리스크가 좋은 결과로 이어질 것이라는 '낙관주의(optimism)'가 증가하며, 이것이 위험 감수 행동을 촉진하는 핵심 기제임을 밝혀냈습니다. 중요한 점은, 이러한 낙관에 기반한 '마지막 한탕' 투자가 실제로는 다른 날에 이루어진 투자에 비해 장기적으로 더 낮은 성과를 보이며 금전적 손실로 이어진다는 사실입니다. 즉, 심리적 편향이 실질적인 재무적 손실을 야기할 수 있음을 보여줍니다.\n\n### B. 연구적 의의:\n\n이 논문은 기존 연구를 반박하기보다는, 고전적인 '종료 효과(ending effect)' 이론을 사회적으로 훨씬 더 보편적이고 중요한 맥락으로 확장하고 정교화했다는 점에서 큰 연구적 의의를 가집니다.\n\n1.  새로운 패러다임의 제시: '과업의 끝'에서 '시간의 끝'으로\n    *   기존의 종료 효과 연구는 주로 실험실 환경에서 '연속된 도박의 마지막 판'과 같이 명확하게 정의된 과업의 끝에서 위험 선호가 증가하는 현상에 집중했습니다. 이는 즉각적인 결과 확인이 가능한 제한된 상황에 국한되는 한계가 있었습니다.\n    *   본 연구는 이러한 개념을 '금요일', '월말' 등 사회적으로 공유되는 주기적인 시간의 경계로 확장했습니다. 이는 결과가 즉각적으로 나타나지 않는 '투자'와 같은 장기적 의사결정에도 심리적 마감 효과가 강력하게 작용함을 보여준 최초의 연구 중 하나입니다. 이는 불확실성 하에서의 선택(choice under uncertainty) 연구에 새로운 관점을 제시합니다.\n\n2.  새로운 심리적 기제(Mechanism) 규명: '손실 회피'가 아닌 '낙관주의'\n    *   기간의 끝에 위험을 감수하는 이유가 '이번 주(혹은 이번 달)의 손실을 만회하려는 마지막 시도'일 것이라는 직관적인 추측과 달리, 이 연구는 '미래에 대한 긍정적 기대감과 낙관주의'가 핵심 동인임을 실험을 통해 밝혔습니다. 즉, 사람들은 \"주말을 앞두고 있으니, 이번 투자는 잘 될 거야!\"와 같은 긍정적 감정에 휩싸여 더 과감한 결정을 내린다는 것입니다. 이는 리스크 의사결정의 감정적, 인지적 요인을 이해하는 데 중요한 기여를 합니다.\n\n3.  현 시대적 상황 및 비즈니스 트렌드와의 연관성\n    *   핀테크(FinTech) 및 디지털 금융 시대의 중요성: 이 연구는 P2P 플랫폼이라는 최신 금융 환경의 실제 데이터를 활용했습니다. 이는 로보어드바이저, 주식 거래 앱 등 개인의 비대면 금융 투자가 보편화된 오늘날 매우 중요한 시사점을 가집니다. 플랫폼 사업자들은 금요일 오후나 월말에 리스크가 높은 상품을 추천하는 마케팅을 강화할 수도 있고, 반대로 투자자 보호를 위해 \"기간의 마지막 날에는 평소보다 과감한 투자를 할 경향이 있습니다. 신중하게 결정하세요.\"와 같은 '넛지(nudge)'를 제공할 수도 있습니다.\n    *   소비자 보호 및 금융 정책: 이 연구는 심리적 편향이 실제 재무적 손실로 이어진다는 것을 명확히 보여줍니다. 이는 금융 감독 기관이나 소비자 보호 단체가 투자자 교육 프로그램을 설계할 때 '시간'이라는 변수가 의사결정에 미치는 영향을 포함해야 함을 시사합니다.\n    *   마케팅 전략에의 활용: 고위험-고수익 상품(예: 암호화폐, 신흥 시장 펀드)을 판매하는 기업은 잠재 고객의 '마지막 한탕 심리'가 극대화되는 금요일이나 월말에 집중적으로 광고나 프로모션을 집행하는 전략을 고려할 수 있습니다.\n\n### C. 저자 백그라운드:\n\n1.  Avni M. Shah (아브니 M. 샤)\n    *   주요 연구 분야: 샤 교수는 행동경제학을 기반으로 한 소비자 금융 의사결정 분야의 세계적인 석학입니다. 특히 돈의 심리학(psychology of money), 지불 방식(payment method)이 소비와 기부에 미치는 영향, 재무적 웰빙(financial well-being) 등을 깊이 있게 연구해 왔습니다. \"현금 없는 사회(cashless society)\"에서 소비자들이 겪는 심리적 변화에 대한 연구로도 유명합니다.\n    *   학력 및 배경: 듀크 대학교(Duke University)에서 마케팅 박사 학위를 받았으며, 이곳은 행동경제학의 대가인 댄 애리얼리(Dan Ariely) 교수가 재직했던 곳으로 행동과학 연구의 세계적인 중심지입니다. 이러한 학문적 배경은 그녀의 연구가 인간의 비합리성과 심리적 편향에 깊이 뿌리내리고 있음을 시사합니다. 현재는 토론토 대학교 로트만 경영대학(University of Toronto, Rotman School of Management)의 마케팅 교수로 재직 중입니다.\n    *   학문적 성향: 그녀의 연구는 실험실에서의 엄격한 인과관계 규명과 실제 현장에서의 대규모 데이터 분석을 결합하여 이론적 깊이와 현실적 적용 가능성을 동시에 추구하는 특징을 보입니다.\n\n2.  Xinlong Li (신롱 리)\n    *   주요 연구 분야: 리 교수는 소비자 재무 의사결정, 행동경제학, 디지털 마케팅, 베이지안 통계 모델링 등을 주로 연구하는 신진 학자입니다. 특히 소비자들이 언제, 왜 재무적으로 어려움을 겪는지에 대한 심리적, 환경적 요인을 탐구하는 데 관심이 많습니다.\n    *   학력 및 배경: 토론토 대학교 로트만 경영대학에서 마케팅 박사 학위를 받았습니다. 이를 통해 아브니 샤 교수가 그의 박사과정 지도교수였을 가능성이 매우 높다고 유추할 수 있습니다. 학계에서는 저명한 지도교수와 그의 제자가 함께 연구를 발전시켜 탑 저널에 논문을 게재하는 것이 일반적인 엘리트 코스입니다. 현재는 코네티컷 대학교 경영대학(University of Connecticut, School of Business)의 마케팅 조교수로 재직 중입니다.\n    *   학문적 성향: 지도교수인 샤 교수의 연구 흐름을 이어받아, 행동과학적 접근법과 최신 계량 분석 기법을 결합하여 복잡한 소비자 행동의 원인을 규명하는 데 강점을 보일 것으로 추정됩니다. 이 논문에서 P2P 데이터라는 대규모 필드 데이터를 분석한 것은 그의 계량적 분석 능력을 보여주는 부분이기도 합니다."
    }
  ]
}